guestrrday/__init__.py
guestrrday/__main__.py
guestrrday/guestrrday.py
guestrrday/stopwords
guestrrday/track/__init__.py
guestrrday/track/track.py
guestrrday/track/tracklist.py
guestrrday/utils.py
guestrrday-0.1.2.dist-info/LICENSE
guestrrday-0.1.2.dist-info/METADATA
guestrrday-0.1.2.dist-info/WHEEL
guestrrday-0.1.2.dist-info/entry_points.txt
guestrrday-0.1.2.dist-info/RECORD
