Metadata-Version: 2.1
Name: guestrrday
Version: 0.1.2
Summary: Retrieve the release date and record label of a set of music tracks with high precision & accuracy. 20,000 guessed so far!
Home-page: https://github.com/n42r/guestrrday
License: MIT
Keywords: music,crate-digging,music discovery
Author: n42r
Author-email: n42r.me@gmail.com
Requires-Python: >=3.10,<4.0
Classifier: License :: OSI Approved :: MIT License
Classifier: Operating System :: OS Independent
Classifier: Programming Language :: Python :: 3
Classifier: Programming Language :: Python :: 3.10
Classifier: Programming Language :: Python :: 3.11
Classifier: Programming Language :: Python :: 3.12
Classifier: Topic :: Multimedia :: Sound/Audio
Requires-Dist: click (>=8.1.7,<9.0.0)
Requires-Dist: discogs-client (>=2.3.0,<3.0.0)
Requires-Dist: pyyaml (>=6.0.1,<7.0.0)
Requires-Dist: unidecode (>=1.3.7,<2.0.0)
Project-URL: Bug Tracker, https://github.com/n42r/guestrrday/issues
